xgrove/__init__.py
xgrove/finalTest.py
xgrove/grove.py
xgrove/roundTest.py
xgrove/sgtree.py
xgrove/xgrove.py
xgrove-1.0.dist-info/LICENSE
xgrove-1.0.dist-info/METADATA
xgrove-1.0.dist-info/WHEEL
xgrove-1.0.dist-info/top_level.txt
xgrove-1.0.dist-info/RECORD
