Metadata-Version: 2.1
Name: xgrove
Version: 1.0
Summary: creating and calculating groves of tree models
Author: Jean Jacques Berry
Author-email: <J.Jacques.Berry@gmail.com>
Keywords: tree,model,grove,forest
Classifier: Development Status :: 1 - Planning
Classifier: Intended Audience :: Developers
Classifier: Programming Language :: Python :: 3
Classifier: Operating System :: Unix
Classifier: Operating System :: MacOS :: MacOS X
Classifier: Operating System :: Microsoft :: Windows
Requires-Python: >=3.6
License-File: LICENSE
Requires-Dist: mkdocs
Requires-Dist: scikit-learn >=0.24.1
Requires-Dist: numpy >=1.19.2
Requires-Dist: matplotlib >=3.3.2
Requires-Dist: pandas >=1.1.3
Requires-Dist: statistics
